{"nodes": [{"id": "smartreport_apps_reports_views_py", "label": "views.py", "file_type": "code", "source_file": "SmartReport/apps/reports/views.py", "source_location": "L1"}, {"id": "views_home", "label": "home()", "file_type": "code", "source_file": "SmartReport/apps/reports/views.py", "source_location": "L9"}], "edges": [{"source": "smartreport_apps_reports_views_py", "target": "django_http", "relation": "imports_from", "confidence": "EXTRACTED", "source_file": "SmartReport/apps/reports/views.py", "source_location": "L1", "weight": 1.0}, {"source": "smartreport_apps_reports_views_py", "target": "django_shortcuts", "relation": "imports_from", "confidence": "EXTRACTED", "source_file": "SmartReport/apps/reports/views.py", "source_location": "L2", "weight": 1.0}, {"source": "smartreport_apps_reports_views_py", "target": "views_home", "relation": "contains", "confidence": "EXTRACTED", "source_file": "SmartReport/apps/reports/views.py", "source_location": "L9", "weight": 1.0}], "raw_calls": [{"caller_nid": "views_home", "callee": "get", "source_file": "SmartReport/apps/reports/views.py", "source_location": "L11"}, {"caller_nid": "views_home", "callee": "HttpResponse", "source_file": "SmartReport/apps/reports/views.py", "source_location": "L12"}, {"caller_nid": "views_home", "callee": "render", "source_file": "SmartReport/apps/reports/views.py", "source_location": "L14"}]}